gyazo_pdf/__init__.py
gyazo_pdf/main.py
gyazo_pdf/processor.py
gyazo_pdf-0.1.2.dist-info/licenses/LICENSE
gyazo_pdf-0.1.2.dist-info/METADATA
gyazo_pdf-0.1.2.dist-info/WHEEL
gyazo_pdf-0.1.2.dist-info/entry_points.txt
gyazo_pdf-0.1.2.dist-info/top_level.txt
gyazo_pdf-0.1.2.dist-info/RECORD
