Metadata-Version: 2.4
Name: gyazo-pdf
Version: 0.1.2
Summary: A Python script to convert PDF pages to images and upload them to Gyazo.
Author-email: yosider <yosider@users.noreply.github.com>
License: MIT
Project-URL: Homepage, https://github.com/yosider/gyazo-pdf
Project-URL: Repository, https://github.com/yosider/gyazo-pdf
Project-URL: Issues, https://github.com/yosider/gyazo-pdf/issues
Keywords: gyazo,pdf
Requires-Python: >=3.10
License-File: LICENSE
Requires-Dist: click
Requires-Dist: Pillow
Requires-Dist: PyMuPDF
Requires-Dist: pyperclip
Requires-Dist: python-dotenv
Requires-Dist: python-gyazo
Requires-Dist: PyYAML
Requires-Dist: tqdm
Dynamic: license-file
